dolphie/App.py
dolphie/DataTypes.py
dolphie/Dolphie.py
dolphie/Dolphie.tcss
dolphie/Modules/ArgumentParser.py
dolphie/Modules/CommandManager.py
dolphie/Modules/CommandPalette.py
dolphie/Modules/Functions.py
dolphie/Modules/KeyEventManager.py
dolphie/Modules/ManualException.py
dolphie/Modules/MetricManager.py
dolphie/Modules/MySQL.py
dolphie/Modules/PerformanceSchemaMetrics.py
dolphie/Modules/Queries.py
dolphie/Modules/ReplayManager.py
dolphie/Modules/TabManager.py
dolphie/Modules/WorkerDataProcessor.py
dolphie/Modules/WorkerManager.py
dolphie/Panels/DDL.py
dolphie/Panels/Dashboard.py
dolphie/Panels/MetadataLocks.py
dolphie/Panels/PerformanceSchemaMetrics.py
dolphie/Panels/Processlist.py
dolphie/Panels/ProxySQLCommandStats.py
dolphie/Panels/ProxySQLDashboard.py
dolphie/Panels/ProxySQLHostgroupSummary.py
dolphie/Panels/ProxySQLProcesslist.py
dolphie/Panels/ProxySQLQueryRules.py
dolphie/Panels/Replication.py
dolphie/Panels/StatementsSummaryMetrics.py
dolphie/Widgets/AutoComplete.py
dolphie/Widgets/CommandModal.py
dolphie/Widgets/CommandScreen.py
dolphie/Widgets/EventLogScreen.py
dolphie/Widgets/ProxySQLThreadScreen.py
dolphie/Widgets/SpinnerWidget.py
dolphie/Widgets/TabSetupModal.py
dolphie/Widgets/ThreadScreen.py
dolphie/Widgets/TopBar.py
dolphie-6.11.4.dist-info/METADATA
dolphie-6.11.4.dist-info/WHEEL
dolphie-6.11.4.dist-info/entry_points.txt
dolphie-6.11.4.dist-info/licenses/LICENSE
dolphie-6.11.4.dist-info/RECORD
