Metadata-Version: 2.4
Name: dolphie
Version: 6.11.4
Summary: Your single pane of glass for real-time analytics into MySQL/MariaDB & ProxySQL
License: GPL-3.0-or-later
License-File: LICENSE
Author: Charles Thompson
Author-email: 01charles.t@gmail.com
Requires-Python: >=3.9,<4.0
Classifier: License :: OSI Approved :: GNU General Public License v3 or later (GPLv3+)
Classifier: Programming Language :: Python :: 3
Classifier: Programming Language :: Python :: 3.9
Classifier: Programming Language :: Python :: 3.10
Classifier: Programming Language :: Python :: 3.11
Classifier: Programming Language :: Python :: 3.12
Classifier: Programming Language :: Python :: 3.13
Classifier: Programming Language :: Python :: 3.14
Requires-Dist: loguru (>=0.7.3,<0.8.0)
Requires-Dist: myloginpath (>=0.0.4,<0.0.5)
Requires-Dist: orjson (>=3.10.15,<4.0.0)
Requires-Dist: packaging (>=25.0,<26.0)
Requires-Dist: plotext (>=5.3.2,<6.0.0)
Requires-Dist: psutil (>=7.1.3,<8.0.0)
Requires-Dist: pymysql (>=1.1.2,<2.0.0)
Requires-Dist: requests (>=2.32.5,<3.0.0)
Requires-Dist: rich (>=14.2.0,<15.0.0)
Requires-Dist: sqlparse (>=0.5.5,<0.6.0)
Requires-Dist: textual (>=6.11.0,<7.0.0)
Requires-Dist: zstandard (>=0.25.0,<0.26.0)
